{
  "_links": {
    "paye": {
      "href": "/individuals/income/paye?matchId=57072660-1df9-4aeb-b4ea-cd2d7f96e430{&startDate,endDate}",
      "title": "Get individual's income per employment"
    },
    "selfAssessment": {
      "href": "/individuals/income/sa?matchId=57072660-1df9-4aeb-b4ea-cd2d7f96e430{&startYear,endYear}",
      "title": "Get individual's self-assessment income"
    },
    "self": {
      "href": "/individuals/income/?matchId=57072660-1df9-4aeb-b4ea-cd2d7f96e430"
    }
  }
}